napari_splinebox/__init__.py
napari_splinebox/_main.py
napari_splinebox/_reader.py
napari_splinebox/_sample_data.py
napari_splinebox/_version.py
napari_splinebox/_widget.py
napari_splinebox/_writer.py
napari_splinebox/napari.yaml
napari_splinebox/_tests/__init__.py
napari_splinebox/_tests/test_reader.py
napari_splinebox/_tests/test_sample_data.py
napari_splinebox/_tests/test_widget.py
napari_splinebox/_tests/test_writer.py
napari_splinebox-0.0.4a0.dist-info/licenses/LICENSE
napari_splinebox-0.0.4a0.dist-info/METADATA
napari_splinebox-0.0.4a0.dist-info/WHEEL
napari_splinebox-0.0.4a0.dist-info/entry_points.txt
napari_splinebox-0.0.4a0.dist-info/top_level.txt
napari_splinebox-0.0.4a0.dist-info/RECORD
