Metadata-Version: 2.4
Name: napari-splinebox
Version: 0.0.4a0
Summary: A plugin to create splines with napari.
Author: Florian Aymanns
Author-email: florian.aymanns@epfl.ch
License: 
Project-URL: Bug Tracker, https://github.com/EPFL-Center-for-Imaging/napari-splinebox/issues
Project-URL: Documentation, https://github.com/EPFL-Center-for-Imaging/napari-splinebox#README.md
Project-URL: Source Code, https://github.com/EPFL-Center-for-Imaging/napari-splinebox
Project-URL: User Support, https://github.com/EPFL-Center-for-Imaging/napari-splinebox/issues
Classifier: Development Status :: 2 - Pre-Alpha
Classifier: Framework :: napari
Classifier: Intended Audience :: Developers
Classifier: License :: OSI Approved :: BSD License
Classifier: Operating System :: OS Independent
Classifier: Programming Language :: Python
Classifier: Programming Language :: Python :: 3
Classifier: Programming Language :: Python :: 3 :: Only
Classifier: Programming Language :: Python :: 3.9
Classifier: Programming Language :: Python :: 3.10
Classifier: Programming Language :: Python :: 3.11
Classifier: Programming Language :: Python :: 3.12
Classifier: Topic :: Scientific/Engineering :: Image Processing
Requires-Python: >=3.9
License-File: LICENSE
Requires-Dist: numpy
Requires-Dist: magicgui
Requires-Dist: qtpy
Requires-Dist: splinebox
Requires-Dist: pandas
Provides-Extra: testing
Requires-Dist: tox; extra == "testing"
Requires-Dist: pytest; extra == "testing"
Requires-Dist: pytest-cov; extra == "testing"
Requires-Dist: pytest-qt; extra == "testing"
Requires-Dist: napari; extra == "testing"
Requires-Dist: pyqt5; extra == "testing"
Dynamic: license-file
